PyCCSDS/__init__.py
PyCCSDS/ccsds.py
Python_CCSDS-0.1.0.dist-info/LICENSE
Python_CCSDS-0.1.0.dist-info/METADATA
Python_CCSDS-0.1.0.dist-info/WHEEL
Python_CCSDS-0.1.0.dist-info/top_level.txt
Python_CCSDS-0.1.0.dist-info/RECORD
