Metadata-Version: 2.1
Name: Python-CCSDS
Version: 0.1.0
Author-email: Romolo Politi <romolo.politi@gmail.com>
License: GNU GPL ver3
Keywords: python,ccsds,nasa,esa,packets
License-File: LICENSE
Requires-Dist: rich
Requires-Dist: bitstring
Requires-Dist: spiceypy
Requires-Dist: importlib-metadata ; python_version > "3.9"
Provides-Extra: docs
Requires-Dist: sphinx ; extra == 'docs'
